{
  "session_id": "S0007",
  "started_at": "2026-01-29T07:38:13Z",
  "last_updated": "2026-01-29T07:38:13Z",
  "status": "active",
  "focus": "Fix bulk actions issues - column persistence, refresh functionality, investigate errors",
  "tasks_snapshot": {
    "total": 19,
    "not_started": 1,
    "in_progress": 1,
    "passing": 17,
    "failing": 0,
    "blocked": 0
  },
  "active_task_ids": [19],
  "blockers": [],
  "notes": "User reported 3 issues: column order not saving, positions not refreshing, two additional errors. Convex function exists in backend (confirmed via function-spec) but api.d.ts types not regenerated. Need to investigate actual runtime errors and fix issues."
}
