{
  "session_id": "S0003",
  "started_at": "2026-01-29T04:00:00Z",
  "last_updated": "2026-01-29T08:30:00Z",
  "status": "active",
  "focus": "Phase 1 & Phase 2 COMPLETE - Auth system and dashboard layout fully implemented",
  "tasks_snapshot": {
    "total": 16,
    "not_started": 0,
    "in_progress": 0,
    "passing": 16,
    "failing": 0,
    "blocked": 0
  },
  "active_task_ids": [],
  "blockers": [],
  "notes": "Phase 1 Foundation: ✓ All components, UI fixes, examples. Phase 2 Auth & Layout: ✓ Convex Auth integration, login page, dashboard layout with SidebarNavigation, auth protection, loading states. Ready for Phase 3: Core Features (Projects, Domains, Keywords CRUD)."
}
