{
  "session_id": "S0029",
  "date": "2026-02-06",
  "tasks": [
    {
      "id": 1,
      "name": "content_gap_detail_modal",
      "status": "passing",
      "created_session": "S0027",
      "last_updated_session": "S0027"
    },
    {
      "id": 2,
      "name": "content_gap_table_rewrite",
      "status": "passing",
      "created_session": "S0027",
      "last_updated_session": "S0027"
    },
    {
      "id": 3,
      "name": "content_gap_tooltips",
      "status": "passing",
      "created_session": "S0027",
      "last_updated_session": "S0027"
    },
    {
      "id": 4,
      "name": "user_system_admin_panel",
      "status": "passing",
      "created_session": "S0027",
      "last_updated_session": "S0028"
    },
    {
      "id": 5,
      "name": "domain_onboarding_system",
      "status": "passing",
      "created_session": "S0029",
      "last_updated_session": "S0029"
    }
  ],
  "reason": "Domain onboarding system implemented: wizard (3-step) + inline checklist + auto-chaining between steps.",
  "thinking_process": "Created 8 new files + edited 1 existing. Schema already had onboarding fields from previous session. All TypeScript checks pass.",
  "connected_tasks": [5],
  "how_to_test": [
    {
      "id": 1,
      "name": "Content Gap table: column visibility, sorting, search, filters, pagination all work",
      "status": "done",
      "is_ok": true,
      "data_for_next_step": [],
      "session_id": "S0027"
    },
    {
      "id": 2,
      "name": "Row click opens detail modal with score breakdown, competitor info, recommendations",
      "status": "done",
      "is_ok": true,
      "data_for_next_step": [],
      "session_id": "S0027"
    },
    {
      "id": 3,
      "name": "Tooltips visible on: section header, summary cards, chart headings, table columns",
      "status": "done",
      "is_ok": true,
      "data_for_next_step": [],
      "session_id": "S0027"
    },
    {
      "id": 4,
      "name": "npx tsc --noEmit passes with zero errors (including all onboarding files)",
      "status": "done",
      "is_ok": true,
      "data_for_next_step": [],
      "session_id": "S0029"
    },
    {
      "id": 10,
      "name": "New domain -> wizard auto-opens with 3 steps: Keywords, Competitors, Analysis",
      "status": "not_started",
      "is_ok": null,
      "data_for_next_step": [],
      "session_id": "S0029"
    },
    {
      "id": 11,
      "name": "Step 1: discovered keywords table, Select Recommended, Add to Monitoring works",
      "status": "not_started",
      "is_ok": null,
      "data_for_next_step": [],
      "session_id": "S0029"
    },
    {
      "id": 12,
      "name": "Step 2: SERP auto-runs, progress bar updates, competitor cards with checkboxes appear",
      "status": "not_started",
      "is_ok": null,
      "data_for_next_step": [],
      "session_id": "S0029"
    },
    {
      "id": 13,
      "name": "Step 3: analysis auto-runs, summary shows counts, Go to Dashboard works",
      "status": "not_started",
      "is_ok": null,
      "data_for_next_step": [],
      "session_id": "S0029"
    },
    {
      "id": 14,
      "name": "After wizard close -> inline checklist shows remaining steps",
      "status": "not_started",
      "is_ok": null,
      "data_for_next_step": [],
      "session_id": "S0029"
    }
  ]
}
